[
  {
    "time": "12:54",
    "Adem_Oencue": 0.295868,
    "Join": 0.203793,
    "KanMind": 0.736502,
    "Coderr": 0.660029
  },
  {
    "time": "18:49",
    "Adem_Oencue": 0.234956,
    "Join": 0.082677,
    "KanMind": 0.510932,
    "Coderr": 0.416957
  },
  {
    "time": "01:47",
    "Adem_Oencue": 0.503673,
    "Join": 0.173848,
    "KanMind": 0.831537,
    "Coderr": 0.822636
  },
  {
    "time": "06:53",
    "Adem_Oencue": 0.338823,
    "Join": 0.107349,
    "KanMind": 0.58432,
    "Coderr": 0.571836
  },
  {
    "time": "12:42",
    "Adem_Oencue": 0.160766,
    "Join": 0.062949,
    "KanMind": 0.473884,
    "Coderr": 0.48525
  },
  {
    "time": "18:33",
    "Adem_Oencue": 0.265252,
    "Join": 0.130275,
    "KanMind": 0.572743,
    "Coderr": 0.439867
  },
  {
    "time": "01:58",
    "Adem_Oencue": 0.350783,
    "Join": 0.144523,
    "KanMind": 0.796344,
    "Coderr": 0.627963
  },
  {
    "time": "06:57",
    "Adem_Oencue": 0.42173,
    "Join": 0.185003,
    "KanMind": 0.749421,
    "Coderr": 0.750443
  },
  {
    "time": "12:43",
    "Adem_Oencue": 0.1211,
    "Join": 0.072944,
    "KanMind": 0.479807,
    "Coderr": 0.473559
  },
  {
    "time": "18:34",
    "Adem_Oencue": 0.246306,
    "Join": 0.07669,
    "KanMind": 0.47516,
    "Coderr": 0.453487
  },
  {
    "time": "02:01",
    "Adem_Oencue": 0.506577,
    "Join": 0.144965,
    "KanMind": 0.712596,
    "Coderr": 0.559801
  },
  {
    "time": "07:20",
    "Adem_Oencue": 0.450057,
    "Join": 0.164042,
    "KanMind": 0.664783,
    "Coderr": 0.567557
  },
  {
    "time": "13:07",
    "Adem_Oencue": 0.349349,
    "Join": 0.163453,
    "KanMind": 0.776626,
    "Coderr": 0.755284
  },
  {
    "time": "18:53",
    "Adem_Oencue": 0.440022,
    "Join": 0.167746,
    "KanMind": 0.736199,
    "Coderr": 0.644587
  },
  {
    "time": "01:56",
    "Adem_Oencue": 0.277646,
    "Join": 0.154552,
    "KanMind": 0.644238,
    "Coderr": 0.641053
  },
  {
    "time": "07:06",
    "Adem_Oencue": 0.125771,
    "Join": 0.100446,
    "KanMind": 0.512677,
    "Coderr": 0.501902
  },
  {
    "time": "13:06",
    "Adem_Oencue": 0.251838,
    "Join": 0.117292,
    "KanMind": 0.55409,
    "Coderr": 0.581232
  },
  {
    "time": "18:55",
    "Adem_Oencue": 0.088381,
    "Join": 0.072645,
    "KanMind": 0.416329,
    "Coderr": 0.419024
  },
  {
    "time": "02:05",
    "Adem_Oencue": 0.229385,
    "Join": 0.094754,
    "KanMind": 0.49758,
    "Coderr": 0.507851
  },
  {
    "time": "07:13",
    "Adem_Oencue": 0.171872,
    "Join": 0.104074,
    "KanMind": 0.574112,
    "Coderr": 0.535672
  },
  {
    "time": "13:09",
    "Adem_Oencue": 0.214814,
    "Join": 0.083352,
    "KanMind": 0.505515,
    "Coderr": 0.521523
  },
  {
    "time": "18:54",
    "Adem_Oencue": 0.267614,
    "Join": 0.063633,
    "KanMind": 0.497091,
    "Coderr": 0.467344
  },
  {
    "time": "01:53",
    "Adem_Oencue": 0.239268,
    "Join": 0.077214,
    "KanMind": 0.478729,
    "Coderr": 0.473997
  },
  {
    "time": "07:05",
    "Adem_Oencue": 0.104156,
    "Join": 0.077122,
    "KanMind": 0.506389,
    "Coderr": 0.476997
  },
  {
    "time": "13:01",
    "Adem_Oencue": 0.345667,
    "Join": 0.141198,
    "KanMind": 0.484206,
    "Coderr": 0.485466
  },
  {
    "time": "18:50",
    "Adem_Oencue": 0.404629,
    "Join": 0.146973,
    "KanMind": 0.646669,
    "Coderr": 0.645352
  },
  {
    "time": "01:54",
    "Adem_Oencue": 0.346783,
    "Join": 0.159228,
    "KanMind": 0.559422,
    "Coderr": 0.569843
  },
  {
    "time": "07:02",
    "Adem_Oencue": 0.233339,
    "Join": 0.081399,
    "KanMind": 0.487131,
    "Coderr": 0.424279
  },
  {
    "time": "12:53",
    "Adem_Oencue": 0.212782,
    "Join": 0.092716,
    "KanMind": 0.506556,
    "Coderr": 0.411668
  },
  {
    "time": "18:39",
    "Adem_Oencue": 0.415526,
    "Join": 0.146536,
    "KanMind": 0.763647,
    "Coderr": 0.691057
  }
]